LICENSE
mkdirpy/__init__.py
mkdirpy/__main__.py
mkdirpy/main.py
mkdirpy-0.1.1.dist-info/entry_points.txt
mkdirpy-0.1.1.dist-info/LICENSE
mkdirpy-0.1.1.dist-info/WHEEL
mkdirpy-0.1.1.dist-info/METADATA
mkdirpy-0.1.1.dist-info/RECORD
